wagtail_blocks/__init__.py
wagtail_blocks/apps.py
wagtail_blocks/blocks.py
wagtail_blocks/locale/ar/LC_MESSAGES/django.po
wagtail_blocks/locale/cn/LC_MESSAGES/django.po
wagtail_blocks/locale/de/LC_MESSAGES/django.po
wagtail_blocks/locale/es/LC_MESSAGES/django.po
wagtail_blocks/locale/fr/LC_MESSAGES/django.po
wagtail_blocks/locale/tr/LC_MESSAGES/django.po
wagtail_blocks/static/wagtail_blocks/.prettierrc
wagtail_blocks/static/wagtail_blocks/README.md
wagtail_blocks/static/wagtail_blocks/css/app.css
wagtail_blocks/static/wagtail_blocks/css/styles.css
wagtail_blocks/static/wagtail_blocks/package-lock.json
wagtail_blocks/static/wagtail_blocks/package.json
wagtail_blocks/templates/wagtail_blocks/blocks/accordion.html
wagtail_blocks/templates/wagtail_blocks/blocks/alert.html
wagtail_blocks/templates/wagtail_blocks/blocks/browser.html
wagtail_blocks/templates/wagtail_blocks/blocks/carousel.html
wagtail_blocks/templates/wagtail_blocks/blocks/code.html
wagtail_blocks/templates/wagtail_blocks/blocks/code_mockup.html
wagtail_blocks/templates/wagtail_blocks/blocks/diff.html
wagtail_blocks/templates/wagtail_blocks/blocks/fab.html
wagtail_blocks/templates/wagtail_blocks/blocks/hover_gallery.html
wagtail_blocks/templates/wagtail_blocks/blocks/image.html
wagtail_blocks/templates/wagtail_blocks/blocks/list.html
wagtail_blocks/templates/wagtail_blocks/blocks/phone.html
wagtail_blocks/templates/wagtail_blocks/blocks/steps.html
wagtail_blocks/templates/wagtail_blocks/blocks/tabs.html
wagtail_blocks/templates/wagtail_blocks/blocks/timeline.html
wagtail_blocks/templates/wagtail_blocks/blocks/toast.html
wagtail_blocks/templates/wagtail_blocks/blocks/window.html
wagtail_blocks/templates/wagtail_blocks/styles.html
wagtail_tw_blocks-0.3.0.dist-info/METADATA
wagtail_tw_blocks-0.3.0.dist-info/WHEEL
wagtail_tw_blocks-0.3.0.dist-info/licenses/LICENSE
wagtail_tw_blocks-0.3.0.dist-info/RECORD
