Metadata-Version: 2.4
Name: wagtail-tw-blocks
Version: 0.3.0
Summary: A collection of reusable, production-ready content blocks for Wagtail CMS, styled with Tailwind CSS and daisyUI.
License: MIT
License-File: LICENSE
Author: Yousef Abu Shanab
Author-email: josephyousef249@gmail.com
Requires-Python: >=3.10
Classifier: License :: OSI Approved :: MIT License
Classifier: Programming Language :: Python :: 3
Classifier: Programming Language :: Python :: 3.10
Classifier: Programming Language :: Python :: 3.11
Classifier: Programming Language :: Python :: 3.12
Classifier: Programming Language :: Python :: 3.13
Classifier: Programming Language :: Python :: 3.14
Requires-Dist: django (>=5.2.1)
Requires-Dist: wagtail (>=7.0)
Project-URL: Documentation, https://github.com/youzarsiph/wagtail-tw-blocks
Project-URL: Homepage, https://github.com/youzarsiph/wagtail-tw-blocks
Project-URL: Repository, https://github.com/youzarsiph/wagtail-tw-blocks
